[
null,
{"id":1,"expanded":true,"name":"oHouse","order":1,"parentId":0,"scrollX":832,"scrollY":640},
{"id":2,"expanded":false,"name":"iHouse","order":2,"parentId":1,"scrollX":832,"scrollY":640},
{"id":3,"expanded":false,"name":"bHouse","order":3,"parentId":2,"scrollX":595.6363636363636,"scrollY":335.27272727272725},
{"id":4,"expanded":false,"name":"NHouse","order":4,"parentId":1,"scrollX":982.8,"scrollY":553.1999999999999},
{"id":5,"expanded":true,"name":"CMap","order":5,"parentId":1,"scrollX":832,"scrollY":640},
{"id":6,"expanded":true,"name":"PInside","order":6,"parentId":5,"scrollX":973.1999999999999,"scrollY":1126.8},
{"id":7,"expanded":false,"name":"RH","order":7,"parentId":6,"scrollX":982.8,"scrollY":553.1999999999999},
{"id":8,"expanded":false,"name":"PBM","order":8,"parentId":6,"scrollX":982.8,"scrollY":553.1999999999999},
{"id":9,"expanded":true,"name":"Bpass","order":9,"parentId":0,"scrollX":973.1999999999999,"scrollY":1088.3999999999999},
{"id":10,"expanded":false,"name":"Inside Bpass","order":10,"parentId":9,"scrollX":982.8,"scrollY":553.1999999999999}
]